klotho/__init__.py
klotho/application.py
klotho/construct.py
klotho/output.py
klotho/provider.py
klotho/runtime.py
klotho/runtime_util.py
klotho/service_pb2.py
klotho/service_pb2_grpc.py
klotho/type_util.py
klotho/urn.py
klotho/aws/__init__.py
klotho/aws/api.py
klotho/aws/bucket.py
klotho/aws/container.py
klotho/aws/dynamodb.py
klotho/aws/fastapi.py
klotho/aws/function.py
klotho/aws/network.py
klotho/aws/postgres.py
klotho/aws/provider.py
klotho-0.1.1.dist-info/LICENSE
klotho-0.1.1.dist-info/METADATA
klotho-0.1.1.dist-info/WHEEL
klotho-0.1.1.dist-info/top_level.txt
klotho-0.1.1.dist-info/RECORD
