Metadata-Version: 2.1
Name: klotho
Version: 0.1.1
Summary: A Python SDK for Klotho2
Author-email: Aaron Torres <atorres@klo.dev>
License: Apache License
Project-URL: Homepage, https://klo.dev
Classifier: Programming Language :: Python :: 3
Classifier: License :: OSI Approved :: Apache Software License
Classifier: Operating System :: OS Independent
Classifier: Development Status :: 2 - Pre-Alpha
Requires-Python: >=3.6
License-File: LICENSE
Requires-Dist: argparse>=1.4.0
Requires-Dist: grpcio>=1.64.0
Requires-Dist: grpcio-tools>=1.64.0
Requires-Dist: protobuf>=5.27.0
Requires-Dist: pyyaml>=6.0.0
Requires-Dist: setuptools>=70
Provides-Extra: dev
Requires-Dist: debugpy<2,>=1.8.1; extra == "dev"
